trianglesolver.py
trianglesolver-1.2.dist-info/LICENSE.txt
trianglesolver-1.2.dist-info/METADATA
trianglesolver-1.2.dist-info/WHEEL
trianglesolver-1.2.dist-info/top_level.txt
trianglesolver-1.2.dist-info/RECORD
