Metadata-Version: 2.1
Name: trianglesolver
Version: 1.2
Summary: Find all the sides and angles of a triangle, if you know some of the sides and/or angles. (Uses the Law of Sines and Law of Cosines.)
Home-page: http://pypi.python.org/pypi/trianglesolver
Author: Steven Byrnes
Author-email: steven.byrnes@gmail.com
License: MIT
Keywords: trigonometry,triangle,law of sines,law of cosines
Platform: UNKNOWN
Classifier: Development Status :: 4 - Beta
Classifier: Intended Audience :: Science/Research
Classifier: Intended Audience :: Education
Classifier: Topic :: Scientific/Engineering :: Mathematics
Classifier: License :: OSI Approved :: MIT License
Classifier: Operating System :: OS Independent
Classifier: Programming Language :: Python :: 2
Classifier: Programming Language :: Python :: 3
